{"add":{"path":"part-00001-5f1b2d6a-4774-42e6-92c9-3718a8c6b7fc-c000.snappy.parquet","partitionValues":{},"size":5353,"modificationTime":1749100661422,"dataChange":true,"stats":"{\"numRecords\":1,\"minValues\":{\"order_id\":\"13c449f4-478d-4f53-9d90-d0f74c6ab84f\",\"event_id\":\"9ac30e79-5af8-431b-95d1-1ca2fc1495bf\",\"timestamp\":\"2025-05-28T23:30:07.799989Z\",\"purchase_product_name\":\"Product A\",\"total_amount\":262.71,\"user_id\":\"user_56\",\"purchase_product_id\":\"product2\",\"price\":453.26,\"purchase_quantity\":2,\"payment_method\":\"bank_transfer\"},\"maxValues\":{\"order_id\":\"13c449f4-478d-4f53-9d90-d0f74c6ab84f\",\"user_id\":\"user_56\",\"price\":453.26,\"total_amount\":262.71,\"event_id\":\"9ac30e79-5af8-431b-95d1-1ca2fc1495bf\",\"timestamp\":\"2025-05-28T23:30:07.799989Z\",\"purchase_product_name\":\"Product A\",\"payment_method\":\"bank_transfer\",\"purchase_product_id\":\"product2\",\"purchase_quantity\":2},\"nullCount\":{\"purchase_product_name\":0,\"price\":0,\"cart_product_id\":1,\"view_product_id\":1,\"total_amount\":0,\"cart_product_name\":1,\"event_id\":0,\"view_product_name\":1,\"view_category\":1,\"cart_quantity\":1,\"timestamp\":0,\"payment_method\":0,\"user_id\":0,\"order_id\":0,\"purchase_product_id\":0,\"purchase_quantity\":0}}","tags":null,"deletionVector":null,"baseRowId":null,"defaultRowCommitVersion":null,"clusteringProvider":null}}
{"commitInfo":{"timestamp":1749100661422,"operation":"MERGE","operationParameters":{"matchedPredicates":"[{\"actionType\":\"update\"}]","mergePredicate":"source.event_id = target.event_id","notMatchedPredicates":"[{\"actionType\":\"insert\"}]","notMatchedBySourcePredicates":"[]"},"clientVersion":"delta-rs.py-0.25.5","readVersion":108,"operationMetrics":{"execution_time_ms":38,"num_output_rows":1,"num_source_rows":1,"num_target_files_added":1,"num_target_files_removed":0,"num_target_files_scanned":66,"num_target_files_skipped_during_scan":0,"num_target_rows_copied":0,"num_target_rows_deleted":0,"num_target_rows_inserted":1,"num_target_rows_updated":0,"rewrite_time_ms":8,"scan_time_ms":0}}}