{"add":{"path":"part-00001-e949036d-a35b-4a94-9433-fc0a6a0e38a8-c000.snappy.parquet","partitionValues":{},"size":5275,"modificationTime":1749100657690,"dataChange":true,"stats":"{\"numRecords\":1,\"minValues\":{\"price\":478.53,\"event_id\":\"a05d8f10-02bd-4f68-a624-1c69d030ddb7\",\"user_id\":\"user_5\",\"purchase_product_id\":\"product3\",\"order_id\":\"24138c15-4685-4db1-a43b-bfb34c01a0bc\",\"payment_method\":\"upi\",\"purchase_product_name\":\"Product C\",\"total_amount\":231.38,\"purchase_quantity\":4,\"timestamp\":\"2025-05-27T20:16:50.561658Z\"},\"maxValues\":{\"purchase_product_id\":\"product3\",\"event_id\":\"a05d8f10-02bd-4f68-a624-1c69d030ddb7\",\"price\":478.53,\"order_id\":\"24138c15-4685-4db1-a43b-bfb34c01a0bc\",\"timestamp\":\"2025-05-27T20:16:50.561658Z\",\"purchase_product_name\":\"Product C\",\"user_id\":\"user_5\",\"total_amount\":231.38,\"payment_method\":\"upi\",\"purchase_quantity\":4},\"nullCount\":{\"view_category\":1,\"cart_product_name\":1,\"timestamp\":0,\"cart_product_id\":1,\"view_product_name\":1,\"order_id\":0,\"total_amount\":0,\"cart_quantity\":1,\"price\":0,\"payment_method\":0,\"view_product_id\":1,\"user_id\":0,\"purchase_product_id\":0,\"purchase_quantity\":0,\"purchase_product_name\":0,\"event_id\":0}}","tags":null,"deletionVector":null,"baseRowId":null,"defaultRowCommitVersion":null,"clusteringProvider":null}}
{"remove":{"path":"part-00001-7ba0549b-f88c-4dd5-a125-77549eff3599-c000.snappy.parquet","dataChange":true,"deletionTimestamp":1749100657690,"extendedFileMetadata":true,"partitionValues":{},"size":5275}}
{"commitInfo":{"timestamp":1749100657690,"operation":"MERGE","operationParameters":{"matchedPredicates":"[{\"actionType\":\"update\"}]","mergePredicate":"source.event_id = target.event_id","notMatchedPredicates":"[{\"actionType\":\"insert\"}]","notMatchedBySourcePredicates":"[]"},"readVersion":39,"operationMetrics":{"execution_time_ms":37,"num_output_rows":1,"num_source_rows":1,"num_target_files_added":1,"num_target_files_removed":1,"num_target_files_scanned":24,"num_target_files_skipped_during_scan":0,"num_target_rows_copied":0,"num_target_rows_deleted":0,"num_target_rows_inserted":0,"num_target_rows_updated":1,"rewrite_time_ms":7,"scan_time_ms":0},"clientVersion":"delta-rs.py-0.25.5"}}