{"add":{"path":"part-00001-fde192c6-21a5-4c04-9b70-96c0be2b2790-c000.snappy.parquet","partitionValues":{},"size":2340,"modificationTime":1748266499471,"dataChange":true,"stats":"{\"numRecords\":50,\"minValues\":{\"year\":2025,\"time_key\":\"2025-05-25T21:41:51.916012Z\",\"hour\":0,\"day\":1,\"month\":5},\"maxValues\":{\"hour\":23,\"time_key\":\"2025-06-25T05:10:05.644646Z\",\"day\":31,\"year\":2025,\"month\":6},\"nullCount\":{\"day\":0,\"time_key\":0,\"year\":0,\"hour\":0,\"month\":0}}","tags":null,"deletionVector":null,"baseRowId":null,"defaultRowCommitVersion":null,"clusteringProvider":null}}
{"add":{"path":"part-00001-3666592d-4fea-48c3-870d-8dc80a358882-c000.snappy.parquet","partitionValues":{},"size":3471,"modificationTime":1748266499471,"dataChange":true,"stats":"{\"numRecords\":150,\"minValues\":{\"year\":2025,\"day\":1,\"hour\":0,\"time_key\":\"2025-05-25T13:19:43.181070Z\",\"month\":5},\"maxValues\":{\"hour\":23,\"year\":2025,\"month\":6,\"time_key\":\"2025-06-25T10:48:35.346334Z\",\"day\":31},\"nullCount\":{\"hour\":0,\"time_key\":0,\"month\":0,\"year\":0,\"day\":0}}","tags":null,"deletionVector":null,"baseRowId":null,"defaultRowCommitVersion":null,"clusteringProvider":null}}
{"remove":{"path":"part-00001-6b93367c-f54a-42fe-9e5a-92610f145a72-c000.snappy.parquet","dataChange":true,"deletionTimestamp":1748266499472,"extendedFileMetadata":true,"partitionValues":{},"size":3470}}
{"commitInfo":{"timestamp":1748266499472,"operation":"MERGE","operationParameters":{"mergePredicate":"source.time_key = target.time_key","notMatchedBySourcePredicates":"[]","notMatchedPredicates":"[{\"actionType\":\"insert\"}]","matchedPredicates":"[{\"actionType\":\"update\"}]"},"operationMetrics":{"execution_time_ms":31,"num_output_rows":200,"num_source_rows":200,"num_target_files_added":2,"num_target_files_removed":1,"num_target_files_scanned":1,"num_target_files_skipped_during_scan":0,"num_target_rows_copied":0,"num_target_rows_deleted":0,"num_target_rows_inserted":50,"num_target_rows_updated":150,"rewrite_time_ms":12,"scan_time_ms":0},"clientVersion":"delta-rs.py-0.25.5","readVersion":1}}