{"add":{"path":"part-00001-376e210d-a33a-4257-b672-f6b2c23b87b4-c000.snappy.parquet","partitionValues":{},"size":10453,"modificationTime":1748280836294,"dataChange":true,"stats":"{\"numRecords\":50,\"minValues\":{\"session_id\":\"0ea400bf-c5de-4a83-9c40-a0166f3b6531\",\"referrer_url\":\"http://beard.info/\",\"page_url\":\"http://charles.com/\",\"ip_address\":\"108.243.8.197\",\"event_id\":\"015d4ad7-553c-4103-a532-1fd3daa61a7f\",\"event_type\":\"button_click\",\"user_id\":\"0b191d35-b309-4cef-a41c-b3f0f89d0f8b\",\"user_agent\":\"Mozilla/5.0 (Android 7.0; Mobile; rv:64.0) Gecko/64.0 Firefox/64.0\",\"event_timestamp\":\"2025-04-27T01:12:13.399299Z\"},\"maxValues\":{\"page_url\":\"https://www.smith.com/\",\"user_id\":\"fbd5ba72-fc92-46bf-9f9a-3d590fe69198\",\"event_timestamp\":\"2025-05-26T07:05:42.789427Z\",\"event_type\":\"page_view\",\"user_agent\":\"Opera/9.79.(Windows NT 6.2; bg-BG) Presto/2.9.187 Version/12.00\",\"session_id\":\"fd8cca11-b45f-4134-a029-ed2e3bb1be9a\",\"ip_address\":\"70.186.255.12\",\"referrer_url\":\"https://www.wu-jones.com/\",\"event_id\":\"dd259654-8d28-48ff-ad19-845d23f91332\"},\"nullCount\":{\"user_agent\":0,\"event_type\":0,\"page_url\":0,\"referrer_url\":26,\"session_id\":0,\"event_timestamp\":0,\"event_id\":0,\"user_id\":28,\"ip_address\":28}}","tags":null,"deletionVector":null,"baseRowId":null,"defaultRowCommitVersion":null,"clusteringProvider":null}}
{"commitInfo":{"timestamp":1748280836294,"operation":"MERGE","operationParameters":{"notMatchedPredicates":"[{\"actionType\":\"insert\"}]","mergePredicate":"source.event_id = target.event_id","notMatchedBySourcePredicates":"[]","matchedPredicates":"[{\"actionType\":\"update\"}]"},"readVersion":9,"operationMetrics":{"execution_time_ms":24,"num_output_rows":50,"num_source_rows":50,"num_target_files_added":1,"num_target_files_removed":0,"num_target_files_scanned":6,"num_target_files_skipped_during_scan":0,"num_target_rows_copied":0,"num_target_rows_deleted":0,"num_target_rows_inserted":50,"num_target_rows_updated":0,"rewrite_time_ms":8,"scan_time_ms":0},"clientVersion":"delta-rs.py-0.25.5"}}